algoz/errors.py
algoz/identification.py
algoz/location.py
algoz/welcome.py
algoz-0.0.3.dist-info/METADATA
algoz-0.0.3.dist-info/WHEEL
algoz-0.0.3.dist-info/entry_points.txt
algoz-0.0.3.dist-info/top_level.txt
algoz-0.0.3.dist-info/RECORD
