Metadata-Version: 2.1
Name: algoz
Version: 0.0.3
Summary: Algorithmia and Threeza interoperability
Home-page: https://github.com/microprediction/algoz
Author: microprediction
Author-email: info@3za.org
License: MIT
Platform: UNKNOWN
Classifier: License :: OSI Approved :: MIT License
Classifier: Programming Language :: Python :: 3
Classifier: Programming Language :: Python :: 3.7
Requires-Dist: Algorithmia
Requires-Dist: threeza
